neural_solution/__init__.py
neural_solution/config.py
neural_solution/launcher.py
neural_solution/version.py
neural_solution/backend/__init__.py
neural_solution/backend/cluster.py
neural_solution/backend/result_monitor.py
neural_solution/backend/runner.py
neural_solution/backend/scheduler.py
neural_solution/backend/task.py
neural_solution/backend/task_db.py
neural_solution/backend/task_monitor.py
neural_solution/backend/utils/__init__.py
neural_solution/backend/utils/utility.py
neural_solution/bin/__init__.py
neural_solution/bin/neural_solution.py
neural_solution/frontend/__init__.py
neural_solution/frontend/task_submitter.py
neural_solution/frontend/user_facing_api.json
neural_solution/frontend/utility.py
neural_solution/frontend/fastapi/__init__.py
neural_solution/frontend/fastapi/main_server.py
neural_solution/frontend/gRPC/__init__.py
neural_solution/frontend/gRPC/client.py
neural_solution/frontend/gRPC/server.py
neural_solution/frontend/gRPC/proto/__init__.py
neural_solution/frontend/gRPC/proto/neural_solution_pb2.py
neural_solution/frontend/gRPC/proto/neural_solution_pb2_grpc.py
neural_solution/scripts/prepare_deps.py
neural_solution/utils/__init__.py
neural_solution/utils/logger.py
neural_solution/utils/utility.py
neural_solution-2.6.1.dist-info/LICENSE
neural_solution-2.6.1.dist-info/METADATA
neural_solution-2.6.1.dist-info/WHEEL
neural_solution-2.6.1.dist-info/entry_points.txt
neural_solution-2.6.1.dist-info/third-party-programs.txt
neural_solution-2.6.1.dist-info/top_level.txt
neural_solution-2.6.1.dist-info/RECORD
